{
  "generatedAt": "2026-02-05T15:01:15.673Z",
  "day": "2025-10-30",
  "groups": [
    {
      "name": "3-1 Mr. Smith 25/26",
      "items": [
        {
          "id": "ann:794983481366:820216250063",
          "title": "Here is our Bookaween coming to life! Thanks for all your effort! Jiwoo, we missed you! Get well soon! 3-1 Class Happ…",
          "link": "https://classroom.google.com/c/Nzk0OTgzNDgxMzY2",
          "dueAt": null,
          "topic": "ANNOUNCEMENT",
          "createdAt": "2025-10-30T08:16:21.961Z"
        }
      ]
    }
  ]
}