{
  "generatedAt": "2026-02-05T15:55:33.948Z",
  "count": 110,
  "earliestTimeKst": "01:12",
  "earliestExample": {
    "day": "2025-12-06",
    "iso": "2025-12-05T16:12:14.337Z",
    "hhmm": "01:12",
    "course": "3-1 Mr. Smith 25/26",
    "id": "ann-day:794983481366:2025-12-06"
  },
  "latestTimeKst": "22:54",
  "latestExample": {
    "day": "2025-11-04",
    "iso": "2025-11-04T13:54:53.929Z",
    "hhmm": "22:54",
    "course": "3-1 Mr. Smith 25/26",
    "id": "ann-day:794983481366:2025-11-04"
  },
  "raw": [
    {
      "day": "2025-08-11",
      "iso": "2025-08-11T11:23:22.363Z",
      "hhmm": "20:23",
      "course": "3-1 Mr. Smith 25/26",
      "id": "ann-day:794983481366:2025-08-11"
    },
    {
      "day": "2025-08-13",
      "iso": "2025-08-13T07:02:44.921Z",
      "hhmm": "16:02",
      "course": "3-1 Mr. Smith 25/26",
      "id": "ann-day:794983481366:2025-08-13"
    },
    {
      "day": "2025-08-14",
      "iso": "2025-08-14T07:10:19.150Z",
      "hhmm": "16:10",
      "course": "3-1 Mr. Smith 25/26",
      "id": "ann-day:794983481366:2025-08-14"
    },
    {
      "day": "2025-08-16",
      "iso": "2025-08-16T06:29:54.059Z",
      "hhmm": "15:29",
      "course": "3-1 Mr. Smith 25/26",
      "id": "ann:794983481366:795479917489"
    },
    {
      "day": "2025-08-18",
      "iso": "2025-08-18T07:14:27.244Z",
      "hhmm": "16:14",
      "course": "3-1 Mr. Smith 25/26",
      "id": "ann-day:794983481366:2025-08-18"
    },
    {
      "day": "2025-08-19",
      "iso": "2025-08-19T05:25:36.452Z",
      "hhmm": "14:25",
      "course": "3-1 Mr. Smith 25/26",
      "id": "ann-day:794983481366:2025-08-19"
    },
    {
      "day": "2025-08-20",
      "iso": "2025-08-20T08:25:32.157Z",
      "hhmm": "17:25",
      "course": "3-1 Mr. Smith 25/26",
      "id": "ann-day:794983481366:2025-08-20"
    },
    {
      "day": "2025-08-21",
      "iso": "2025-08-21T04:30:40.122Z",
      "hhmm": "13:30",
      "course": "3-1 Mr. Smith 25/26",
      "id": "ann-day:794983481366:2025-08-21"
    },
    {
      "day": "2025-08-22",
      "iso": "2025-08-22T04:46:56.251Z",
      "hhmm": "13:46",
      "course": "3-1 Mr. Smith 25/26",
      "id": "ann-day:794983481366:2025-08-22"
    },
    {
      "day": "2025-08-25",
      "iso": "2025-08-25T07:15:44.912Z",
      "hhmm": "16:15",
      "course": "3-1 Mr. Smith 25/26",
      "id": "ann-day:794983481366:2025-08-25"
    },
    {
      "day": "2025-08-26",
      "iso": "2025-08-26T07:40:59.591Z",
      "hhmm": "16:40",
      "course": "3-1 Mr. Smith 25/26",
      "id": "ann-day:794983481366:2025-08-26"
    },
    {
      "day": "2025-08-27",
      "iso": "2025-08-27T07:05:52.698Z",
      "hhmm": "16:05",
      "course": "3-1 Mr. Smith 25/26",
      "id": "ann-day:794983481366:2025-08-27"
    },
    {
      "day": "2025-08-28",
      "iso": "2025-08-28T06:47:08.409Z",
      "hhmm": "15:47",
      "course": "3-1 Mr. Smith 25/26",
      "id": "ann-day:794983481366:2025-08-28"
    },
    {
      "day": "2025-08-29",
      "iso": "2025-08-29T05:50:05.106Z",
      "hhmm": "14:50",
      "course": "3-1 Mr. Smith 25/26",
      "id": "ann-day:794983481366:2025-08-29"
    },
    {
      "day": "2025-08-31",
      "iso": "2025-08-31T13:12:29.145Z",
      "hhmm": "22:12",
      "course": "3-1 Mr. Smith 25/26",
      "id": "ann:794983481366:796102416721"
    },
    {
      "day": "2025-09-01",
      "iso": "2025-09-01T06:27:50.339Z",
      "hhmm": "15:27",
      "course": "3-1 Mr. Smith 25/26",
      "id": "ann-day:794983481366:2025-09-01"
    },
    {
      "day": "2025-09-02",
      "iso": "2025-09-02T07:00:14.041Z",
      "hhmm": "16:00",
      "course": "3-1 Mr. Smith 25/26",
      "id": "ann-day:794983481366:2025-09-02"
    },
    {
      "day": "2025-09-03",
      "iso": "2025-09-03T06:33:21.524Z",
      "hhmm": "15:33",
      "course": "3-1 Mr. Smith 25/26",
      "id": "ann-day:794983481366:2025-09-03"
    },
    {
      "day": "2025-09-04",
      "iso": "2025-09-04T07:01:44.534Z",
      "hhmm": "16:01",
      "course": "3-1 Mr. Smith 25/26",
      "id": "ann-day:794983481366:2025-09-04"
    },
    {
      "day": "2025-09-05",
      "iso": "2025-09-05T04:53:59.017Z",
      "hhmm": "13:53",
      "course": "3-1 Mr. Smith 25/26",
      "id": "ann-day:794983481366:2025-09-05"
    },
    {
      "day": "2025-09-08",
      "iso": "2025-09-08T06:28:18.644Z",
      "hhmm": "15:28",
      "course": "3-1 Mr. Smith 25/26",
      "id": "ann-day:794983481366:2025-09-08"
    },
    {
      "day": "2025-09-09",
      "iso": "2025-09-09T05:51:02.067Z",
      "hhmm": "14:51",
      "course": "3-1 Mr. Smith 25/26",
      "id": "ann-day:794983481366:2025-09-09"
    },
    {
      "day": "2025-09-10",
      "iso": "2025-09-10T07:03:54.635Z",
      "hhmm": "16:03",
      "course": "3-1 Mr. Smith 25/26",
      "id": "ann-day:794983481366:2025-09-10"
    },
    {
      "day": "2025-09-11",
      "iso": "2025-09-11T07:13:11.092Z",
      "hhmm": "16:13",
      "course": "3-1 Mr. Smith 25/26",
      "id": "ann-day:794983481366:2025-09-11"
    },
    {
      "day": "2025-09-12",
      "iso": "2025-09-12T06:00:49.126Z",
      "hhmm": "15:00",
      "course": "3-1 Mr. Smith 25/26",
      "id": "ann-day:794983481366:2025-09-12"
    },
    {
      "day": "2025-09-15",
      "iso": "2025-09-15T06:06:50.798Z",
      "hhmm": "15:06",
      "course": "3-1 Mr. Smith 25/26",
      "id": "ann-day:794983481366:2025-09-15"
    },
    {
      "day": "2025-09-16",
      "iso": "2025-09-16T06:46:46.334Z",
      "hhmm": "15:46",
      "course": "3-1 Mr. Smith 25/26",
      "id": "ann-day:794983481366:2025-09-16"
    },
    {
      "day": "2025-09-17",
      "iso": "2025-09-17T07:06:06.184Z",
      "hhmm": "16:06",
      "course": "3-1 Mr. Smith 25/26",
      "id": "ann-day:794983481366:2025-09-17"
    },
    {
      "day": "2025-09-18",
      "iso": "2025-09-18T07:08:51.101Z",
      "hhmm": "16:08",
      "course": "3-1 Mr. Smith 25/26",
      "id": "ann-day:794983481366:2025-09-18"
    },
    {
      "day": "2025-09-19",
      "iso": "2025-09-19T04:33:14.811Z",
      "hhmm": "13:33",
      "course": "3-1 Mr. Smith 25/26",
      "id": "ann-day:794983481366:2025-09-19"
    },
    {
      "day": "2025-09-21",
      "iso": "2025-09-21T07:12:05.724Z",
      "hhmm": "16:12",
      "course": "3-1 Mr. Smith 25/26",
      "id": "ann-day:794983481366:2025-09-21"
    },
    {
      "day": "2025-09-22",
      "iso": "2025-09-22T07:01:19.963Z",
      "hhmm": "16:01",
      "course": "3-1 Mr. Smith 25/26",
      "id": "ann-day:794983481366:2025-09-22"
    },
    {
      "day": "2025-09-23",
      "iso": "2025-09-23T04:01:32.149Z",
      "hhmm": "13:01",
      "course": "3-1 Mr. Smith 25/26",
      "id": "ann-day:794983481366:2025-09-23"
    },
    {
      "day": "2025-09-24",
      "iso": "2025-09-24T04:53:12.707Z",
      "hhmm": "13:53",
      "course": "3-1 Mr. Smith 25/26",
      "id": "ann-day:794983481366:2025-09-24"
    },
    {
      "day": "2025-09-25",
      "iso": "2025-09-25T07:24:39.222Z",
      "hhmm": "16:24",
      "course": "3-1 Mr. Smith 25/26",
      "id": "ann-day:794983481366:2025-09-25"
    },
    {
      "day": "2025-09-26",
      "iso": "2025-09-26T06:46:15.412Z",
      "hhmm": "15:46",
      "course": "3-1 Mr. Smith 25/26",
      "id": "ann-day:794983481366:2025-09-26"
    },
    {
      "day": "2025-09-29",
      "iso": "2025-09-29T04:23:07.310Z",
      "hhmm": "13:23",
      "course": "3-1 Mr. Smith 25/26",
      "id": "ann-day:794983481366:2025-09-29"
    },
    {
      "day": "2025-09-30",
      "iso": "2025-09-30T07:00:38.324Z",
      "hhmm": "16:00",
      "course": "3-1 Mr. Smith 25/26",
      "id": "ann-day:794983481366:2025-09-30"
    },
    {
      "day": "2025-10-01",
      "iso": "2025-10-01T08:19:19.765Z",
      "hhmm": "17:19",
      "course": "3-1 Mr. Smith 25/26",
      "id": "ann-day:794983481366:2025-10-01"
    },
    {
      "day": "2025-10-02",
      "iso": "2025-10-02T05:38:02.695Z",
      "hhmm": "14:38",
      "course": "3-1 Mr. Smith 25/26",
      "id": "ann-day:794983481366:2025-10-02"
    },
    {
      "day": "2025-10-07",
      "iso": "2025-10-07T13:48:34.006Z",
      "hhmm": "22:48",
      "course": "3-1 Mr. Smith 25/26",
      "id": "ann-day:794983481366:2025-10-07"
    },
    {
      "day": "2025-10-14",
      "iso": "2025-10-14T05:50:16.518Z",
      "hhmm": "14:50",
      "course": "3-1 Mr. Smith 25/26",
      "id": "ann-day:794983481366:2025-10-14"
    },
    {
      "day": "2025-10-15",
      "iso": "2025-10-15T08:01:55.927Z",
      "hhmm": "17:01",
      "course": "3-1 Mr. Smith 25/26",
      "id": "ann-day:794983481366:2025-10-15"
    },
    {
      "day": "2025-10-16",
      "iso": "2025-10-16T08:26:29.320Z",
      "hhmm": "17:26",
      "course": "3-1 Mr. Smith 25/26",
      "id": "ann-day:794983481366:2025-10-16"
    },
    {
      "day": "2025-10-17",
      "iso": "2025-10-17T04:51:58.608Z",
      "hhmm": "13:51",
      "course": "3-1 Mr. Smith 25/26",
      "id": "ann-day:794983481366:2025-10-17"
    },
    {
      "day": "2025-10-20",
      "iso": "2025-10-20T12:49:41.995Z",
      "hhmm": "21:49",
      "course": "3-1 Mr. Smith 25/26",
      "id": "ann-day:794983481366:2025-10-20"
    },
    {
      "day": "2025-10-21",
      "iso": "2025-10-21T06:35:21.155Z",
      "hhmm": "15:35",
      "course": "3-1 Mr. Smith 25/26",
      "id": "ann-day:794983481366:2025-10-21"
    },
    {
      "day": "2025-10-22",
      "iso": "2025-10-22T07:12:06.545Z",
      "hhmm": "16:12",
      "course": "3-1 Mr. Smith 25/26",
      "id": "ann-day:794983481366:2025-10-22"
    },
    {
      "day": "2025-10-23",
      "iso": "2025-10-23T07:58:56.134Z",
      "hhmm": "16:58",
      "course": "3-1 Mr. Smith 25/26",
      "id": "ann-day:794983481366:2025-10-23"
    },
    {
      "day": "2025-10-24",
      "iso": "2025-10-24T04:54:12.253Z",
      "hhmm": "13:54",
      "course": "3-1 Mr. Smith 25/26",
      "id": "ann-day:794983481366:2025-10-24"
    },
    {
      "day": "2025-10-27",
      "iso": "2025-10-27T11:35:27.764Z",
      "hhmm": "20:35",
      "course": "3-1 Mr. Smith 25/26",
      "id": "ann-day:794983481366:2025-10-27"
    },
    {
      "day": "2025-10-28",
      "iso": "2025-10-28T06:31:09.403Z",
      "hhmm": "15:31",
      "course": "3-1 Mr. Smith 25/26",
      "id": "ann-day:794983481366:2025-10-28"
    },
    {
      "day": "2025-10-29",
      "iso": "2025-10-29T06:13:58.064Z",
      "hhmm": "15:13",
      "course": "3-1 Mr. Smith 25/26",
      "id": "ann-day:794983481366:2025-10-29"
    },
    {
      "day": "2025-10-30",
      "iso": "2025-10-30T08:16:21.961Z",
      "hhmm": "17:16",
      "course": "3-1 Mr. Smith 25/26",
      "id": "ann:794983481366:820216250063"
    },
    {
      "day": "2025-11-03",
      "iso": "2025-11-03T07:56:32.412Z",
      "hhmm": "16:56",
      "course": "3-1 Mr. Smith 25/26",
      "id": "ann-day:794983481366:2025-11-03"
    },
    {
      "day": "2025-11-04",
      "iso": "2025-11-04T13:54:53.929Z",
      "hhmm": "22:54",
      "course": "3-1 Mr. Smith 25/26",
      "id": "ann-day:794983481366:2025-11-04"
    },
    {
      "day": "2025-11-06",
      "iso": "2025-11-06T10:33:43.992Z",
      "hhmm": "19:33",
      "course": "3-1 Mr. Smith 25/26",
      "id": "ann-day:794983481366:2025-11-06"
    },
    {
      "day": "2025-11-07",
      "iso": "2025-11-07T10:02:31.410Z",
      "hhmm": "19:02",
      "course": "3-1 Mr. Smith 25/26",
      "id": "ann-day:794983481366:2025-11-07"
    },
    {
      "day": "2025-11-10",
      "iso": "2025-11-10T06:32:11.331Z",
      "hhmm": "15:32",
      "course": "3-1 Mr. Smith 25/26",
      "id": "ann-day:794983481366:2025-11-10"
    },
    {
      "day": "2025-11-11",
      "iso": "2025-11-11T07:28:03.487Z",
      "hhmm": "16:28",
      "course": "3-1 Mr. Smith 25/26",
      "id": "ann-day:794983481366:2025-11-11"
    },
    {
      "day": "2025-11-12",
      "iso": "2025-11-12T06:14:07.710Z",
      "hhmm": "15:14",
      "course": "3-1 Mr. Smith 25/26",
      "id": "ann-day:794983481366:2025-11-12"
    },
    {
      "day": "2025-11-13",
      "iso": "2025-11-13T05:47:03.527Z",
      "hhmm": "14:47",
      "course": "3-1 Mr. Smith 25/26",
      "id": "ann-day:794983481366:2025-11-13"
    },
    {
      "day": "2025-11-14",
      "iso": "2025-11-14T01:17:57.154Z",
      "hhmm": "10:17",
      "course": "3-1 Mr. Smith 25/26",
      "id": "ann-day:794983481366:2025-11-14"
    },
    {
      "day": "2025-11-15",
      "iso": "2025-11-15T01:36:43.063Z",
      "hhmm": "10:36",
      "course": "3-1 Mr. Smith 25/26",
      "id": "ann:794983481366:820754767367"
    },
    {
      "day": "2025-11-16",
      "iso": "2025-11-16T07:15:34.180Z",
      "hhmm": "16:15",
      "course": "3-1 Mr. Smith 25/26",
      "id": "ann:794983481366:828785464262"
    },
    {
      "day": "2025-11-17",
      "iso": "2025-11-17T06:59:18.407Z",
      "hhmm": "15:59",
      "course": "3-1 Mr. Smith 25/26",
      "id": "ann-day:794983481366:2025-11-17"
    },
    {
      "day": "2025-11-18",
      "iso": "2025-11-18T07:02:00.590Z",
      "hhmm": "16:02",
      "course": "3-1 Mr. Smith 25/26",
      "id": "ann-day:794983481366:2025-11-18"
    },
    {
      "day": "2025-11-19",
      "iso": "2025-11-19T06:28:53.178Z",
      "hhmm": "15:28",
      "course": "3-1 Mr. Smith 25/26",
      "id": "ann-day:794983481366:2025-11-19"
    },
    {
      "day": "2025-11-20",
      "iso": "2025-11-20T05:23:17.110Z",
      "hhmm": "14:23",
      "course": "3-1 Mr. Smith 25/26",
      "id": "ann-day:794983481366:2025-11-20"
    },
    {
      "day": "2025-11-21",
      "iso": "2025-11-21T01:06:19.812Z",
      "hhmm": "10:06",
      "course": "3-1 Mr. Smith 25/26",
      "id": "ann-day:794983481366:2025-11-21"
    },
    {
      "day": "2025-11-24",
      "iso": "2025-11-24T06:40:14.839Z",
      "hhmm": "15:40",
      "course": "3-1 Mr. Smith 25/26",
      "id": "ann-day:794983481366:2025-11-24"
    },
    {
      "day": "2025-11-25",
      "iso": "2025-11-25T05:49:30.229Z",
      "hhmm": "14:49",
      "course": "3-1 Mr. Smith 25/26",
      "id": "ann-day:794983481366:2025-11-25"
    },
    {
      "day": "2025-11-26",
      "iso": "2025-11-26T06:22:42.719Z",
      "hhmm": "15:22",
      "course": "3-1 Mr. Smith 25/26",
      "id": "ann-day:794983481366:2025-11-26"
    },
    {
      "day": "2025-12-01",
      "iso": "2025-12-01T06:47:00.260Z",
      "hhmm": "15:47",
      "course": "3-1 Mr. Smith 25/26",
      "id": "ann-day:794983481366:2025-12-01"
    },
    {
      "day": "2025-12-02",
      "iso": "2025-12-02T06:16:55.325Z",
      "hhmm": "15:16",
      "course": "3-1 Mr. Smith 25/26",
      "id": "ann-day:794983481366:2025-12-02"
    },
    {
      "day": "2025-12-03",
      "iso": "2025-12-03T07:15:55.525Z",
      "hhmm": "16:15",
      "course": "3-1 Mr. Smith 25/26",
      "id": "ann-day:794983481366:2025-12-03"
    },
    {
      "day": "2025-12-04",
      "iso": "2025-12-04T07:07:58.124Z",
      "hhmm": "16:07",
      "course": "3-1 Mr. Smith 25/26",
      "id": "ann-day:794983481366:2025-12-04"
    },
    {
      "day": "2025-12-06",
      "iso": "2025-12-05T16:12:14.337Z",
      "hhmm": "01:12",
      "course": "3-1 Mr. Smith 25/26",
      "id": "ann-day:794983481366:2025-12-06"
    },
    {
      "day": "2025-12-08",
      "iso": "2025-12-08T01:18:34.793Z",
      "hhmm": "10:18",
      "course": "3-1 Mr. Smith 25/26",
      "id": "ann-day:794983481366:2025-12-08"
    },
    {
      "day": "2025-12-09",
      "iso": "2025-12-09T05:44:21.111Z",
      "hhmm": "14:44",
      "course": "3-1 Mr. Smith 25/26",
      "id": "ann-day:794983481366:2025-12-09"
    },
    {
      "day": "2025-12-10",
      "iso": "2025-12-10T06:58:17.356Z",
      "hhmm": "15:58",
      "course": "3-1 Mr. Smith 25/26",
      "id": "ann-day:794983481366:2025-12-10"
    },
    {
      "day": "2025-12-11",
      "iso": "2025-12-11T05:47:35.003Z",
      "hhmm": "14:47",
      "course": "3-1 Mr. Smith 25/26",
      "id": "ann-day:794983481366:2025-12-11"
    },
    {
      "day": "2025-12-12",
      "iso": "2025-12-12T08:22:05.234Z",
      "hhmm": "17:22",
      "course": "3-1 Mr. Smith 25/26",
      "id": "ann-day:794983481366:2025-12-12"
    },
    {
      "day": "2025-12-26",
      "iso": "2025-12-25T17:18:05.415Z",
      "hhmm": "02:18",
      "course": "3-1 Mr. Smith 25/26",
      "id": "ann:794983481366:823994068709"
    },
    {
      "day": "2026-01-04",
      "iso": "2026-01-04T04:10:16.285Z",
      "hhmm": "13:10",
      "course": "3-1 Mr. Smith 25/26",
      "id": "ann-day:794983481366:2026-01-04"
    },
    {
      "day": "2026-01-05",
      "iso": "2026-01-05T07:30:00.115Z",
      "hhmm": "16:30",
      "course": "3-1 Mr. Smith 25/26",
      "id": "ann-day:794983481366:2026-01-05"
    },
    {
      "day": "2026-01-06",
      "iso": "2026-01-06T09:52:00.811Z",
      "hhmm": "18:52",
      "course": "3-1 Mr. Smith 25/26",
      "id": "ann-day:794983481366:2026-01-06"
    },
    {
      "day": "2026-01-07",
      "iso": "2026-01-07T09:58:23.856Z",
      "hhmm": "18:58",
      "course": "3-1 Mr. Smith 25/26",
      "id": "ann-day:794983481366:2026-01-07"
    },
    {
      "day": "2026-01-08",
      "iso": "2026-01-08T07:58:50.128Z",
      "hhmm": "16:58",
      "course": "3-1 Mr. Smith 25/26",
      "id": "ann-day:794983481366:2026-01-08"
    },
    {
      "day": "2026-01-09",
      "iso": "2026-01-09T05:09:52.676Z",
      "hhmm": "14:09",
      "course": "3-1 Mr. Smith 25/26",
      "id": "ann-day:794983481366:2026-01-09"
    },
    {
      "day": "2026-01-12",
      "iso": "2026-01-12T07:02:19.905Z",
      "hhmm": "16:02",
      "course": "3-1 Mr. Smith 25/26",
      "id": "ann-day:794983481366:2026-01-12"
    },
    {
      "day": "2026-01-13",
      "iso": "2026-01-13T05:46:18.694Z",
      "hhmm": "14:46",
      "course": "3-1 Mr. Smith 25/26",
      "id": "ann-day:794983481366:2026-01-13"
    },
    {
      "day": "2026-01-14",
      "iso": "2026-01-14T03:43:00.173Z",
      "hhmm": "12:43",
      "course": "3-1 Mr. Smith 25/26",
      "id": "ann-day:794983481366:2026-01-14"
    },
    {
      "day": "2026-01-15",
      "iso": "2026-01-15T08:12:44.146Z",
      "hhmm": "17:12",
      "course": "3-1 Mr. Smith 25/26",
      "id": "ann-day:794983481366:2026-01-15"
    },
    {
      "day": "2026-01-16",
      "iso": "2026-01-16T06:34:28.969Z",
      "hhmm": "15:34",
      "course": "3-1 Mr. Smith 25/26",
      "id": "ann-day:794983481366:2026-01-16"
    },
    {
      "day": "2026-01-19",
      "iso": "2026-01-19T06:48:19.941Z",
      "hhmm": "15:48",
      "course": "3-1 Mr. Smith 25/26",
      "id": "ann-day:794983481366:2026-01-19"
    },
    {
      "day": "2026-01-21",
      "iso": "2026-01-21T05:52:14.602Z",
      "hhmm": "14:52",
      "course": "3-1 Mr. Smith 25/26",
      "id": "ann-day:794983481366:2026-01-21"
    },
    {
      "day": "2026-01-22",
      "iso": "2026-01-22T06:49:45.799Z",
      "hhmm": "15:49",
      "course": "3-1 Mr. Smith 25/26",
      "id": "ann-day:794983481366:2026-01-22"
    },
    {
      "day": "2026-01-23",
      "iso": "2026-01-23T07:00:38.252Z",
      "hhmm": "16:00",
      "course": "3-1 Mr. Smith 25/26",
      "id": "ann-day:794983481366:2026-01-23"
    },
    {
      "day": "2026-01-26",
      "iso": "2026-01-26T06:50:13.555Z",
      "hhmm": "15:50",
      "course": "3-1 Mr. Smith 25/26",
      "id": "ann-day:794983481366:2026-01-26"
    },
    {
      "day": "2026-01-27",
      "iso": "2026-01-27T06:32:03.801Z",
      "hhmm": "15:32",
      "course": "3-1 Mr. Smith 25/26",
      "id": "ann-day:794983481366:2026-01-27"
    },
    {
      "day": "2026-01-28",
      "iso": "2026-01-28T04:04:28.932Z",
      "hhmm": "13:04",
      "course": "3-1 Mr. Smith 25/26",
      "id": "ann-day:794983481366:2026-01-28"
    },
    {
      "day": "2026-01-29",
      "iso": "2026-01-29T06:27:14.349Z",
      "hhmm": "15:27",
      "course": "3-1 Mr. Smith 25/26",
      "id": "ann-day:794983481366:2026-01-29"
    },
    {
      "day": "2026-01-30",
      "iso": "2026-01-30T05:04:34.038Z",
      "hhmm": "14:04",
      "course": "3-1 Mr. Smith 25/26",
      "id": "ann-day:794983481366:2026-01-30"
    },
    {
      "day": "2026-02-01",
      "iso": "2026-02-01T01:37:23.357Z",
      "hhmm": "10:37",
      "course": "3-1 Mr. Smith 25/26",
      "id": "ann:794983481366:842371917835"
    },
    {
      "day": "2026-02-01",
      "iso": "2026-02-01T03:38:21.102Z",
      "hhmm": "12:38",
      "course": "3-1 Mr. Smith 25/26",
      "id": "ann:794983481366:842376627683"
    },
    {
      "day": "2026-02-02",
      "iso": "2026-02-02T06:16:20.226Z",
      "hhmm": "15:16",
      "course": "3-1 Mr. Smith 25/26",
      "id": "ann-day:794983481366:2026-02-02"
    },
    {
      "day": "2026-02-03",
      "iso": "2026-02-03T05:14:03.109Z",
      "hhmm": "14:14",
      "course": "3-1 Mr. Smith 25/26",
      "id": "ann-day:794983481366:2026-02-03"
    },
    {
      "day": "2026-02-04",
      "iso": "2026-02-04T06:45:57.528Z",
      "hhmm": "15:45",
      "course": "3-1 Mr. Smith 25/26",
      "id": "ann-day:794983481366:2026-02-04"
    },
    {
      "day": "2026-02-05",
      "iso": "2026-02-05T07:20:28.279Z",
      "hhmm": "16:20",
      "course": "3-1 Mr. Smith 25/26",
      "id": "ann-day:794983481366:2026-02-05"
    }
  ]
}